yclade/__init__.py
yclade/__main__.py
yclade/_yclade.py
yclade/const.py
yclade/find.py
yclade/find_test.py
yclade/snps.py
yclade/snps_test.py
yclade/tree.py
yclade/tree_test.py
yclade/types.py
yclade-0.5.0.dist-info/licenses/LICENSE
yclade-0.5.0.dist-info/METADATA
yclade-0.5.0.dist-info/WHEEL
yclade-0.5.0.dist-info/top_level.txt
yclade-0.5.0.dist-info/RECORD
