Metadata-Version: 2.4
Name: yclade
Version: 0.5.0
Summary: A Python library to find the position on the human Y chromosome tree given a set of single nucleotide polymorphisms (SNPs).
Author-email: David Straub <straub@protonmail.com>
License: MIT
Requires-Python: >=3.9
License-File: LICENSE
Requires-Dist: platformdirs
Requires-Dist: networkx
Provides-Extra: test
Requires-Dist: pytest>=8.0.0; extra == "test"
Requires-Dist: mypy; extra == "test"
Requires-Dist: click; extra == "test"
Dynamic: license-file
